{
  "/_app": "pages/_app.js",
  "/_error": "pages/_error.js",
  "/_document": "pages/_document.js",
  "/": "pages/index.js",
  "/admin/dashboard": "pages/admin/dashboard.js",
  "/admin/upload": "pages/admin/upload.js",
  "/admin/files": "pages/admin/files.js",
  "/admin": "pages/admin.js",
  "/api/data/[...slug]": "pages/api/data/[...slug].js",
  "/admin/diary": "pages/admin/diary.js",
  "/admin/settings": "pages/admin/settings.js",
  "/admin/info": "pages/admin/info.js",
  "/admin/todos": "pages/admin/todos.js",
  "/admin/backup": "pages/admin/backup.js"
}